rich_color_ext/__init__.py
rich_color_ext/cli.py
rich_color_ext/css.py
rich_color_ext/hex_utils.py
rich_color_ext/logger.py
rich_color_ext/patch.py
rich_color_ext/py.typed
rich_color_ext-0.1.9.dist-info/METADATA
rich_color_ext-0.1.9.dist-info/WHEEL
rich_color_ext-0.1.9.dist-info/entry_points.txt
rich_color_ext-0.1.9.dist-info/RECORD
