Metadata-Version: 2.4
Name: rich-color-ext
Version: 0.1.9
Summary: Extend Rich with the ability to parse CSS color names and 3-digit hex colors.
Author-email: Max Ludden <dev@maxludden.com>
License: MIT
Keywords: 3-digit hex,color,color names,css,hex,rich
Classifier: Development Status :: 4 - Beta
Classifier: Intended Audience :: Developers
Classifier: License :: OSI Approved :: MIT License
Classifier: Programming Language :: Python :: 3.10
Classifier: Programming Language :: Python :: 3.11
Classifier: Programming Language :: Python :: 3.12
Classifier: Programming Language :: Python :: 3.13
Classifier: Programming Language :: Python :: 3.14
Requires-Python: >=3.10
Requires-Dist: loguru>=0.7.3
Requires-Dist: pytest>=8.4.0
Requires-Dist: rich>=14.0.0
